{
    "type": "FeatureCollection",
    "features": [
        {
            "type": "Feature",
            "properties": {
                "CC": "Biomassehof",
                "Name": "Biomassehof",
                "shape": "Marker",
                "Hauptsitz": true
            },
            "geometry": {
                "type": "Point",
                "coordinates": [
                    10.311002,
                    47.754614
                ]
            }
        }
    ]
}