{
    "type": "FeatureCollection",
    "features": [
        {
            "type": "Feature",
            "properties": {
                "CC": "Schetter",
                "Name": "Schetter",
                "shape": "Marker",
                "Hauptsitz": true
            },
            "geometry": {
                "type": "Point",
                "coordinates": [
                    9.341158,
                    48.79526
                ]
            }
        }
    ]
}