{
    "type": "FeatureCollection",
    "features": [
        {
            "type": "Feature",
            "properties": {
                "CC": "Schmoll",
                "Name": "Schmoll",
                "shape": "Marker",
                "Hauptsitz": true
            },
            "geometry": {
                "type": "Point",
                "coordinates": [
                    11.057621,
                    49.449347
                ]
            }
        }
    ]
}